MusicalMusic/__init__.py
MusicalMusic/exceptions.py
MusicalMusic/main.py
MusicalMusic/search.py
MusicalMusic-0.2.2.dist-info/DESCRIPTION.rst
MusicalMusic-0.2.2.dist-info/METADATA
MusicalMusic-0.2.2.dist-info/RECORD
MusicalMusic-0.2.2.dist-info/WHEEL
MusicalMusic-0.2.2.dist-info/metadata.json
MusicalMusic-0.2.2.dist-info/top_level.txt
